<?xml version="1.0" encoding="UTF-8"?>
<ti:app xmlns:ti="http://ti.appcelerator.org">
<id>com.mobiten.gym_mama</id>
<name>gym_mama</name>
<version>1.0</version>
<publisher>leonyeh</publisher>
<url>http://mobiten.com</url>
<description>No description provided</description>
<copyright>2011 by leonyeh</copyright>
<icon>default_app_logo.png</icon>
    <persistent-wifi>false</persistent-wifi>
    <prerendered-icon>false</prerendered-icon>
    <statusbar-style>default</statusbar-style>
    <statusbar-hidden>false</statusbar-hidden>
    <fullscreen>false</fullscreen>
    <navbar-hidden>false</navbar-hidden>
    <analytics>true</analytics>
<guid>61bb2ace-d593-4afd-8e9f-7a66767b3425</guid>
	<iphone>
		<orientations device="iphone">
			<orientation>Ti.UI.PORTRAIT</orientation>
		</orientations>
		<orientations device="ipad">
			<orientation>Ti.UI.PORTRAIT</orientation>
			<orientation>Ti.UI.UPSIDE_PORTRAIT</orientation>
			<orientation>Ti.UI.LANDSCAPE_LEFT</orientation>
			<orientation>Ti.UI.LANDSCAPE_RIGHT</orientation>
		</orientations>
	</iphone>
	<android xmlns:android="http://schemas.android.com/apk/res/android">
	</android>
	<modules>
	</modules>
</ti:app>
